nonebot_plugin_gamedraw/__init__.py
nonebot_plugin_gamedraw/build_image.py
nonebot_plugin_gamedraw/config.py
nonebot_plugin_gamedraw/count_manager.py
nonebot_plugin_gamedraw/handles/azur_handle.py
nonebot_plugin_gamedraw/handles/ba_handle.py
nonebot_plugin_gamedraw/handles/base_handle.py
nonebot_plugin_gamedraw/handles/fgo_handle.py
nonebot_plugin_gamedraw/handles/genshin_handle.py
nonebot_plugin_gamedraw/handles/guardian_handle.py
nonebot_plugin_gamedraw/handles/onmyoji_handle.py
nonebot_plugin_gamedraw/handles/pcr_handle.py
nonebot_plugin_gamedraw/handles/pretty_handle.py
nonebot_plugin_gamedraw/handles/prts_handle.py
nonebot_plugin_gamedraw/resources/fonts/gorga.otf
nonebot_plugin_gamedraw/resources/fonts/msyh.ttf
nonebot_plugin_gamedraw/util.py
nonebot_plugin_gamedraw-0.4.3.dist-info/LICENSE
nonebot_plugin_gamedraw-0.4.3.dist-info/WHEEL
nonebot_plugin_gamedraw-0.4.3.dist-info/METADATA
nonebot_plugin_gamedraw-0.4.3.dist-info/RECORD
