Metadata-Version: 2.1
Name: nonebot-plugin-gamedraw
Version: 0.4.3
Summary: nonebot2 实现自动更新的 原神/明日方舟/赛马娘/坎公骑冠剑/公主连结/碧蓝航线/FGO/阴阳师 抽卡插件
Home-page: https://github.com/HibiKier/nonebot_plugin_gamedraw
License: MIT
Author: HibiKier
Author-email: 775757368@qq.com
Requires-Python: >=3.7.3,<4.0.0
Classifier: License :: OSI Approved :: MIT License
Classifier: Programming Language :: Python :: 3
Classifier: Programming Language :: Python :: 3.10
Classifier: Programming Language :: Python :: 3.8
Classifier: Programming Language :: Python :: 3.9
Requires-Dist: Pillow (>=9.0.0,<10.0.0)
Requires-Dist: aiofiles (>=0.8.0,<0.9.0)
Requires-Dist: aiohttp (>=3.7.4,<4.0.0)
Requires-Dist: beautifulsoup4 (>=4.11.1,<5.0.0)
Requires-Dist: cachetools (>=5.0.0,<6.0.0)
Requires-Dist: cn2an (>=0.5.16,<0.6.0)
Requires-Dist: dateparser (>=1.1.0,<2.0.0)
Requires-Dist: lxml (>=4.6.3,<5.0.0)
Requires-Dist: nonebot-adapter-onebot (>=2.0.0-beta.1,<3.0.0)
Requires-Dist: nonebot-plugin-apscheduler (>=0.2.0,<0.3.0)
Requires-Dist: nonebot2 (>=2.0.0-beta.1,<3.0.0)
Requires-Dist: pypinyin (>=0.42.0)
Requires-Dist: typing-extensions (>=3.10.0,<5.0.0)
Requires-Dist: ujson (>=5.1.0,<6.0.0)
Project-URL: Repository, https://github.com/HibiKier/nonebot_plugin_gamedraw
